aminodorks/__init__.py
aminodorks/_client.py
aminodorks/_sub_client.py
aminodorks/services/__init__.py
aminodorks/services/_amino_service.py
aminodorks/services/_dorks_service.py
aminodorks/services/_headers_builder.py
aminodorks/services/_singleton.py
aminodorks/structures/__init__.py
aminodorks/structures/_account.py
aminodorks/structures/_auth_structure.py
aminodorks/structures/_community_structure.py
aminodorks/structures/_link_info_structure.py
aminodorks/structures/_member_structure.py
aminodorks/structures/_thread_structure.py
aminodorks/structures/_user_profile_structure.py
aminodorks/utils/__init__.py
aminodorks/utils/_constants.py
aminodorks/utils/_crypt.py
aminodorks_py-0.0.1b10.dist-info/licenses/LICENSE
aminodorks_py-0.0.1b10.dist-info/METADATA
aminodorks_py-0.0.1b10.dist-info/WHEEL
aminodorks_py-0.0.1b10.dist-info/top_level.txt
aminodorks_py-0.0.1b10.dist-info/RECORD
